ghostimports/__init__.py
ghostimports/builtin_modules.py
ghostimports/cli.py
ghostimports/core.py
ghostimports/registry.py
ghostimports/setup_ipython.py
ghostimports-0.2.0.dist-info/METADATA
ghostimports-0.2.0.dist-info/WHEEL
ghostimports-0.2.0.dist-info/entry_points.txt
ghostimports-0.2.0.dist-info/top_level.txt
ghostimports-0.2.0.dist-info/RECORD
